hello_pip/__init__.py
hello_pip/main.py
sheds_wrapper/__init__.py
sheds_wrapper/main.py
shreds_wrapper-0.1.0.dist-info/LICENSE
shreds_wrapper-0.1.0.dist-info/METADATA
shreds_wrapper-0.1.0.dist-info/WHEEL
shreds_wrapper-0.1.0.dist-info/top_level.txt
shreds_wrapper-0.1.0.dist-info/RECORD
